rf_calc/__init__.py
rf_calc/search_rf.py
receptive_field_calculation-0.0.0.dev1.dist-info/METADATA
receptive_field_calculation-0.0.0.dev1.dist-info/WHEEL
receptive_field_calculation-0.0.0.dev1.dist-info/top_level.txt
receptive_field_calculation-0.0.0.dev1.dist-info/RECORD
